confens/__init__.py
confens/classifiers/Classifier.py
confens/classifiers/ConfidenceBagging.py
confens/classifiers/ConfidenceBaggingParallel.py
confens/classifiers/ConfidenceBoosting.py
confens/classifiers/__init__.py
confens/metrics/DiversityMetric.py
confens/metrics/EnsembleMetric.py
confens/metrics/__init__.py
confens/tests/__init__.py
confens/tests/example_supervised.py
confens/tests/example_unsupervised.py
confens/tests/rq1-2.py
confens/tests/rq3.py
confens/utils/__init__.py
confens/utils/general_utils.py
confens-0.4.dist-info/LICENSE.txt
confens-0.4.dist-info/METADATA
confens-0.4.dist-info/WHEEL
confens-0.4.dist-info/top_level.txt
confens-0.4.dist-info/RECORD
