Metadata-Version: 2.1
Name: confens
Version: 0.4
Summary: Confidence Ensembles to Improve Classification
Home-page: https://github.com/tommyippoz/confidence-ensembles
Author: Tommaso Zoppi
Author-email: tommaso.zoppi@unitn.it
Keywords: machine learning,confidence,safety,ensemble
Classifier: Programming Language :: Python :: 3
Classifier: License :: OSI Approved :: MIT License
Classifier: Operating System :: OS Independent
License-File: LICENSE.txt
